write_the/__about__.py
write_the/__init__.py
write_the/__main__.py
write_the/errors.py
write_the/llm.py
write_the/models.py
write_the/utils.py
write_the/cli/__init__.py
write_the/cli/main.py
write_the/cli/model.py
write_the/cli/tasks.py
write_the/commands/__init__.py
write_the/commands/converters/__init__.py
write_the/commands/converters/converters.py
write_the/commands/converters/prompts.py
write_the/commands/docs/__init__.py
write_the/commands/docs/docs.py
write_the/commands/docs/prompts.py
write_the/commands/docs/utils.py
write_the/commands/mkdocs/__init__.py
write_the/commands/mkdocs/mkdocs.py
write_the/commands/mkdocs/templates.py
write_the/commands/tests/__init__.py
write_the/commands/tests/prompts.py
write_the/commands/tests/tests.py
write_the/cst/__init__.py
write_the/cst/docstring_adder.py
write_the/cst/docstring_remover.py
write_the/cst/function_and_class_collector.py
write_the/cst/node_batcher.py
write_the/cst/node_extractor.py
write_the/cst/node_remover.py
write_the/cst/utils.py
write_the-0.13.0.dist-info/METADATA
write_the-0.13.0.dist-info/WHEEL
write_the-0.13.0.dist-info/entry_points.txt
write_the-0.13.0.dist-info/licenses/LICENSE.txt
write_the-0.13.0.dist-info/RECORD
