Metadata-Version: 2.4
Name: write-the
Version: 0.13.0
Summary: AI-powered Code Generation and Refactoring Tool
Project-URL: Documentation, https://github.com/wytamma/write-the#readme
Project-URL: Issues, https://github.com/wytamma/write-the/issues
Project-URL: Source, https://github.com/wytamma/write-the
Author-email: wytamma <wytamma.wirth@me.com>
License-Expression: MIT
License-File: LICENSE.txt
Classifier: Development Status :: 4 - Beta
Classifier: Programming Language :: Python
Classifier: Programming Language :: Python :: 3.9
Classifier: Programming Language :: Python :: 3.10
Classifier: Programming Language :: Python :: 3.11
Classifier: Programming Language :: Python :: Implementation :: CPython
Classifier: Programming Language :: Python :: Implementation :: PyPy
Requires-Python: >=3.9
Requires-Dist: black==23.11.0
Requires-Dist: langchain==0.0.333
Requires-Dist: libcst==1.1.0
Requires-Dist: openai==0.28.1
Requires-Dist: tiktoken==0.5.1
Requires-Dist: typer==0.15.4
